{
    "id": "1ea45c42ea5734a0b25547af11d908b187ebc372f657ca3aa70afa5e32292745",
    "metadata": "List of state leaders in the 20th century BC | Africa: Northeast | Egypt: Middle Kingdom",
    "metadata_info": "Concatenation of page title, section title and table caption.",
    "header": [
        "Type_",
        "Name_",
        "Title",
        "Royal_house",
        "From_"
    ],
    "cell": [
        [
            "Sovereign",
            "Mentuhotep II",
            "Pharaoh",
            "Eleventh dynasty",
            "2010 BC"
        ],
        [
            "Sovereign",
            "Mentuhotep IV",
            "Pharaoh",
            "Eleventh dynasty",
            "1998 BC or 1997 BC"
        ],
        [
            "Sovereign",
            "Amenemhat I",
            "Pharaoh",
            "Twelfth dynasty",
            "1991 BC"
        ],
        [
            "Sovereign",
            "Senusret I",
            "Pharaoh",
            "Twelfth dynasty",
            "1971 BC"
        ],
        [
            "Sovereign",
            "Amenemhat II",
            "Pharaoh",
            "Twelfth dynasty",
            "1929 BC"
        ]
    ]
}