{
    "id": "727629b82c2804dc7b500c859935f500fee051287b1ecb3f1b9047bf640ede67",
    "metadata": "1964 American Football League Draft | Notable undrafted players | Notable undrafted players",
    "metadata_info": "Concatenation of page title, section title and table caption.",
    "header": [
        "Original_NFL_team",
        "Player",
        "Pos_",
        "College",
        "Conf_"
    ],
    "cell": [
        [
            "Denver Broncos",
            "John Amos Category:Articles with hCards",
            "RB",
            "Colorado State",
            "Ind."
        ],
        [
            "Houston Oilers",
            "Willie Frazier Category:Articles with hCards",
            "TE",
            "Arkansas-Pine Bluff",
            "SWAC"
        ],
        [
            "Houston Oilers",
            "W.K. Hicks Category:Articles with hCards",
            "CB",
            "Texas Southern",
            "SWAC"
        ],
        [
            "Kansas City Chiefs",
            "Mack Lee Hill Category:Articles with hCards \u2020",
            "FB",
            "Southern",
            "SWAC"
        ],
        [
            "Kansas City Chiefs",
            "Willie Mitchell Category:Articles with hCards",
            "CB",
            "Tennessee State",
            "Midwestern"
        ],
        [
            "New York Jets",
            "Bill Rademacher Category:Articles with hCards",
            "WR",
            "Northern Michigan",
            "N/A"
        ],
        [
            "New York Jets",
            "John Schmitt Category:Articles with hCards",
            "C",
            "Hofstra",
            "N/A"
        ],
        [
            "San Diego Chargers",
            "Speedy Duncan Category:Articles with hCards \u2020",
            "CB",
            "Jackson State",
            "SWAC"
        ],
        [
            "San Diego Chargers",
            "Jimmy Warren Category:Articles with hCards \u2020",
            "CB",
            "Illinois",
            "Big Ten"
        ]
    ]
}