{
    "id": "e162847dad2684b2d4bbf550425b7f11e9898ec2d5f8da62f9618ad372e1c0ff",
    "metadata": "2007 FedEx Cup Playoffs | Regular season rankings | Regular season rankings",
    "metadata_info": "Concatenation of page title, section title and table caption.",
    "header": [
        "_",
        "Player",
        "Country",
        "Points",
        "Events",
        "Reset_Points"
    ],
    "cell": [
        [
            "1",
            "Tiger Woods",
            "United States",
            "30574",
            "13",
            "100000"
        ],
        [
            "2",
            "Vijay Singh",
            "Fiji",
            "19129",
            "23",
            "99000"
        ],
        [
            "3",
            "Jim Furyk",
            "United States",
            "16691",
            "19",
            "98500"
        ],
        [
            "4",
            "Phil Mickelson",
            "United States",
            "16037",
            "18",
            "98000"
        ],
        [
            "5",
            "K.J. Choi",
            "South Korea",
            "15485",
            "21",
            "97500"
        ],
        [
            "6",
            "Rory Sabbatini",
            "South Africa",
            "13548",
            "19",
            "97250"
        ],
        [
            "7",
            "Zach Johnson",
            "United States",
            "13341",
            "19",
            "97000"
        ],
        [
            "8",
            "Charles Howell III",
            "United States",
            "12126",
            "21",
            "96750"
        ],
        [
            "9",
            "Brandt Snedeker",
            "United States",
            "11870",
            "25",
            "96500"
        ]
    ]
}