{
    "id": "04e919fbdcf10ca4f7578c3d913c578d93cc1fa24b4025c381ea034eb0b31fc9",
    "metadata": "1994-95 FA Cup | Sixth round proper | Sixth round proper",
    "metadata_info": "Concatenation of page title, section title and table caption.",
    "header": [
        "Tie_no",
        "Home_team",
        "Score",
        "Away_team",
        "Attendance"
    ],
    "cell": [
        [
            "1",
            "Liverpool",
            "1-2",
            "Tottenham Hotspur",
            "39592"
        ],
        [
            "2",
            "Everton",
            "1-0",
            "Newcastle United",
            "12 March 1995"
        ],
        [
            "3",
            "Manchester United",
            "2-0",
            "Queens Park Rangers",
            "12 March 1995"
        ],
        [
            "4",
            "Crystal Palace",
            "1-1",
            "Wolverhampton Wanderers",
            "11 March 1995"
        ],
        [
            "Replay",
            "Wolverhampton Wanderers",
            "1-4",
            "Crystal Palace",
            "22 March 1995"
        ]
    ]
}