{
    "id": "49ee3ddd9dee313ec8482c761b14b86a06d4c385353e1433860afbc16a30538c",
    "metadata": "Middle High German verbs | Strong Verb Vowel Alternation Table | Strong Verb Vowel Alternation Table",
    "metadata_info": "Concatenation of page title, section title and table caption.",
    "header": [
        "Inf_Stem",
        "Sing_Pres_",
        "Plur_Pres_",
        "Sing_Pret_",
        "Plur_Pret_",
        "Subj_Pres_",
        "Subj_Pret_",
        "Past_Part_"
    ],
    "cell": [
        [
            "\u00ee",
            "\u00ee",
            "\u00ee",
            "ei",
            "i",
            "\u00ee",
            "i",
            "i"
        ],
        [
            "\u00ee + h,w",
            "\u00ee",
            "\u00ee",
            "\u00ea",
            "i",
            "\u00ee",
            "i",
            "i"
        ],
        [
            "ie",
            "iu",
            "ie",
            "ou",
            "u",
            "ie",
            "\u00fc",
            "o"
        ],
        [
            "\u00fb",
            "\u00fb",
            "\u00fb",
            "ou",
            "u",
            "\u00fb",
            "\u00fc",
            "o"
        ],
        [
            "iuw",
            "iuw",
            "iuw",
            "ou",
            "\u00fbw",
            "iuw",
            "iu",
            "\u00fbw"
        ],
        [
            "ie + d,t,s,z,h",
            "iu",
            "ie",
            "\u00f4",
            "u",
            "ie",
            "\u00fc",
            "o"
        ],
        [
            "i + m/n + Cons.",
            "i",
            "i",
            "a",
            "u",
            "i",
            "\u00fc",
            "u"
        ],
        [
            "e + l/r + Cons.",
            "i",
            "e",
            "a",
            "u",
            "e",
            "\u00fc",
            "o"
        ],
        [
            "e + m,n,l,r,ch",
            "i",
            "e",
            "a",
            "\u00e2",
            "e",
            "\u00e6",
            "o"
        ],
        [
            "o + m",
            "o/u",
            "o",
            "a",
            "\u00e2",
            "o/u",
            "\u00e6",
            "o"
        ],
        [
            "e",
            "i",
            "e",
            "a",
            "\u00e2",
            "e",
            "\u00e6",
            "e"
        ],
        [
            "i",
            "i",
            "i",
            "a",
            "\u00e2",
            "i",
            "\u00e6",
            "e"
        ],
        [
            "a",
            "a/e",
            "a",
            "uo",
            "uo",
            "a",
            "\u00fce",
            "a"
        ],
        [
            "e",
            "e",
            "e",
            "uo",
            "uo",
            "e",
            "\u00fce",
            "a/o"
        ],
        [
            "a",
            "a/(e)",
            "a",
            "ie",
            "ie",
            "a",
            "ie",
            "a"
        ],
        [
            "\u00e2",
            "\u00e2/(\u00e6)",
            "\u00e2",
            "ie",
            "ie",
            "\u00e2",
            "ie",
            "\u00e2"
        ],
        [
            "ei",
            "ei",
            "ei",
            "ie",
            "ie",
            "ei",
            "ie",
            "ei"
        ],
        [
            "\u00f4",
            "\u00f4",
            "\u00f4",
            "ie",
            "ie",
            "\u00f4",
            "ie",
            "\u00f4"
        ],
        [
            "ou",
            "ou",
            "ou",
            "ie",
            "ie",
            "ou",
            "ie",
            "ou"
        ],
        [
            "uo",
            "uo",
            "uo",
            "ie",
            "ie",
            "uo",
            "ie",
            "uo"
        ]
    ]
}