{
    "id": "9a8bb8615f1f5c3c1f096994621c9e91de0b102e1ec2e0af7de20308fd69fb19",
    "metadata": "Mid-American Collegiate Hockey Association | Gold Division | Gold Division",
    "metadata_info": "Concatenation of page title, section title and table caption.",
    "header": [
        "Institution",
        "Location_",
        "Founded",
        "Affiliation",
        "Enrollment",
        "Nickname"
    ],
    "cell": [
        [
            "University of Illinois",
            "Urbana, IL",
            "1867",
            "Public",
            "42606",
            "Fighting Illini"
        ],
        [
            "Illinois State University",
            "Normal, IL",
            "1857",
            "Public",
            "20859",
            "Redbirds"
        ],
        [
            "University of Iowa",
            "Iowa City, IA",
            "1847",
            "Public",
            "20907",
            "Hawkeyes"
        ],
        [
            "University of Missouri",
            "Columbia, MO",
            "1839",
            "Public",
            "30831",
            "Tigers"
        ],
        [
            "Missouri State University",
            "Springfield, MO",
            "1905",
            "Public",
            "22785",
            "Ice Bears"
        ],
        [
            "Northern Illinois University",
            "DeKalb, IL",
            "1895",
            "Public",
            "25313",
            "Huskies"
        ],
        [
            "Saint Louis University",
            "St. Louis, MO",
            "1818",
            "Private/Catholic",
            "10633",
            "Billikens"
        ],
        [
            "Southern Illinois University Edwardsville",
            "Edwardsville, IL",
            "1957",
            "Public",
            "13398",
            "Cougars"
        ]
    ],
    "source": "Open-WikiTable"
}