{
    "id": "0f3e16ef44c85bb7c530af07f0e3033ffbeb83b5f4d5893be4090cfb3df64168",
    "metadata": "1988-89 Dundee United F.C. season | Premier Division | Premier Division",
    "metadata_info": "Concatenation of page title, section title and table caption.",
    "header": [
        "Date_",
        "Opponent",
        "Venue",
        "Result_",
        "Attendance"
    ],
    "cell": [
        [
            "13 August 1988",
            "St. Mirren",
            "A",
            "1-0",
            "5832"
        ],
        [
            "20 August 1988",
            "Celtic",
            "H",
            "1-0",
            "18769"
        ],
        [
            "27 August 1988",
            "Aberdeen",
            "H",
            "2-2",
            "13128"
        ],
        [
            "3 September 1988",
            "Dundee",
            "A",
            "3-0",
            "14927"
        ],
        [
            "17 September 1988",
            "Hibernian",
            "H",
            "1-1",
            "11017"
        ],
        [
            "24 September 1988",
            "Motherwell",
            "A",
            "2-1",
            "3559"
        ],
        [
            "27 September 1988",
            "Rangers",
            "H",
            "0-1",
            "20071"
        ],
        [
            "1 October 1988",
            "Hearts",
            "H",
            "0-0",
            "10838"
        ],
        [
            "8 October 1988",
            "Hamilton",
            "A",
            "4-0",
            "3538"
        ],
        [
            "12 October 1988",
            "Celtic",
            "A",
            "0-1",
            "36870"
        ],
        [
            "22 October 1988",
            "St. Mirren",
            "H",
            "0-1",
            "7618"
        ],
        [
            "29 October 1988",
            "Motherwell",
            "H",
            "1-1",
            "6266"
        ],
        [
            "2 November 1988",
            "Hibernian",
            "A",
            "1-1",
            "10000"
        ],
        [
            "5 November 1988",
            "Dundee",
            "H",
            "2-0",
            "14882"
        ],
        [
            "12 November 1988",
            "Aberdeen",
            "A",
            "1-1",
            "15000"
        ],
        [
            "19 November 1988",
            "Hearts",
            "A",
            "0-0",
            "10121"
        ],
        [
            "26 November 1988",
            "Hamilton",
            "H",
            "1-0",
            "6357"
        ],
        [
            "3 December 1988",
            "Rangers",
            "A",
            "1-0",
            "39200"
        ],
        [
            "10 December 1988",
            "Hibernian",
            "H",
            "4-1",
            "9963"
        ],
        [
            "17 December 1988",
            "Celtic",
            "H",
            "2-0",
            "18745"
        ],
        [
            "31 December 1988",
            "St. Mirren",
            "A",
            "1-0",
            "7762"
        ],
        [
            "3 January 1989",
            "Aberdeen",
            "H",
            "1-1",
            "17952"
        ],
        [
            "7 January 1989",
            "Dundee",
            "A",
            "1-0",
            "16332"
        ],
        [
            "14 January 1989",
            "Hamilton",
            "A",
            "5-0",
            "4000"
        ],
        [
            "21 January 1989",
            "Hearts",
            "H",
            "0-0",
            "13674"
        ],
        [
            "11 February 1989",
            "Rangers",
            "H",
            "1-1",
            "20013"
        ],
        [
            "11 March 1989",
            "St. Mirren",
            "H",
            "1-4",
            "8320"
        ],
        [
            "14 March 1989",
            "Motherwell",
            "A",
            "2-1",
            "3545"
        ],
        [
            "25 March 1989",
            "Celtic",
            "A",
            "0-1",
            "36870"
        ],
        [
            "1 April 1989",
            "Aberdeen",
            "A",
            "0-1",
            "16700"
        ],
        [
            "8 April 1989",
            "Dundee",
            "H",
            "2-1",
            "11910"
        ],
        [
            "22 April 1989",
            "Motherwell",
            "H",
            "1-1",
            "6301"
        ],
        [
            "29 April 1989",
            "Hibernian",
            "A",
            "2-1",
            "7700"
        ],
        [
            "2 May 1989",
            "Rangers",
            "A",
            "0-2",
            "39058"
        ],
        [
            "6 May 1989",
            "Hearts",
            "A",
            "0-0",
            "8613"
        ],
        [
            "13 May 1989",
            "Hamilton",
            "H",
            "0-1",
            "11503"
        ]
    ],
    "source": "Open-WikiTable"
}