{
    "id": "627a6c67db21e9084b714667e45e8a89977262171766576fa23c38dceb15f254",
    "metadata": "Henry Lau | Variety | Variety",
    "metadata_info": "Concatenation of page title, section title and table caption.",
    "header": [
        "Year_",
        "Network",
        "Title",
        "Notes",
        "Language_"
    ],
    "cell": [
        [
            "2007",
            "SBS",
            "Star King",
            "Guest",
            "Korean"
        ],
        [
            "2008",
            "CCTV",
            "\u52c7\u5f80\u76f4\u524d",
            "Guest",
            "Mandarin Chinese"
        ],
        [
            "2009",
            "CTV",
            "Variety Big Brother",
            "Guest",
            "Mandarin Chinese"
        ],
        [
            "2009",
            "HBS",
            "Happy Camp",
            "Guest",
            "Mandarin Chinese"
        ],
        [
            "2009",
            "SBS",
            "Star King",
            "Guest",
            "Korean"
        ],
        [
            "2011",
            "SBS",
            "Strong Heart",
            "Guest",
            "Korean"
        ],
        [
            "2011",
            "CCTV",
            "\u5f00\u5fc3\u6b4c\u8ff7\u6c47",
            "Guest",
            "Mandarin Chinese"
        ],
        [
            "2011",
            "CTV",
            "Variety Big Brother",
            "Guest",
            "Mandarin Chinese"
        ],
        [
            "2013",
            "Olive TV",
            "MasterChef Korea Celebrity",
            "Celebrity Participant",
            "Korean"
        ],
        [
            "2013",
            "HBS",
            "Happy Camp",
            "Guest",
            "Mandarin Chinese"
        ],
        [
            "2013",
            "KBS2",
            "Happy Together",
            "Guest",
            "Korean"
        ],
        [
            "2013",
            "KBS",
            "Hello Counselor",
            "Guest",
            "Korean"
        ],
        [
            "2013",
            "KBS",
            "Mamma Mia",
            "Guest",
            "Korean"
        ]
    ],
    "source": "Open-WikiTable"
}