{
    "id": "0a1908fa56e779f660e55700f327b197f9f08e12eb2295928e7b4e030e44017f",
    "metadata": "List of herbaria in Europe | British Isles | Herbaria in the British Isles",
    "metadata_info": "Concatenation of page title, section title and table caption.",
    "header": [
        "Name_",
        "No_Specimens",
        "Abbr_",
        "Country",
        "City"
    ],
    "cell": [
        [
            "Royal Botanic Gardens Kew",
            "7000000",
            "K",
            "UK",
            "Kew , England"
        ],
        [
            "British Museum of Natural History",
            "5200000",
            "BM",
            "UK",
            "London, England"
        ],
        [
            "Royal Botanic Garden, Edinburgh",
            "2000000",
            "E",
            "UK",
            "Edinburgh , Scotland"
        ],
        [
            "University of Cambridge",
            "1000000",
            "CGE",
            "UK",
            "Cambridge , England"
        ],
        [
            "University of Manchester",
            "1000000",
            "MANCH",
            "UK",
            "Manchester , England"
        ],
        [
            "National Botanic Gardens, Ireland",
            "600000",
            "DBN",
            "Ireland",
            "Dublin"
        ],
        [
            "National Museums & Galleries of Wales",
            "550000",
            "NMW",
            "UK",
            "Cardiff , Wales"
        ],
        [
            "Fielding-Druce Herbarium, University of Oxford",
            "500000",
            "OXF",
            "UK",
            "Oxford , England"
        ],
        [
            "CABI Bioscience UK Centre",
            "385000",
            "IMI",
            "UK",
            "Surrey , England"
        ],
        [
            "World Museum Liverpool",
            "350000",
            "LIV",
            "UK",
            "Liverpool , England"
        ],
        [
            "Daubeny Herbarium, University of Oxford",
            "300000",
            "FHO",
            "UK",
            "Oxford , England"
        ],
        [
            "University of Reading",
            "254000",
            "RNG",
            "UK",
            "Reading , England"
        ],
        [
            "Trinity College",
            "230000",
            "TCD",
            "Ireland",
            "Dublin"
        ],
        [
            "University of Birmingham",
            "150000",
            "BIRM",
            "UK",
            "Birmingham , England"
        ],
        [
            "University of Leicester",
            "125000",
            "LTR",
            "UK",
            "Leicester , England"
        ],
        [
            "University of Aberdeen",
            "120000",
            "ABD",
            "UK",
            "Aberdeen , Scotland"
        ],
        [
            "South London Botanical Institute",
            "100000",
            "SLBI",
            "UK",
            "London, England"
        ],
        [
            "Nottingham Natural History Museum",
            "91000",
            "NOT",
            "UK",
            "Nottingham , England"
        ],
        [
            "Leicestershire Museums",
            "90000",
            "LSR",
            "UK",
            "Leicester , England"
        ],
        [
            "British Antarctic Survey",
            "40000",
            "AAS",
            "UK",
            "Cambridge , England"
        ],
        [
            "Derby Museum and Art Gallery",
            "8000",
            "DBY",
            "UK",
            "Derby , England"
        ],
        [
            "Charterhouse School Herbarium",
            "8000",
            "GOD",
            "UK",
            "Godalming , England"
        ]
    ],
    "source": "Open-WikiTable"
}