{
    "id": "c5440d5dadf1b5f0a75b4345c403701968b373d4b52d3499c59bbcffdb6f4226",
    "metadata": "Georgian grammar | Possessive adjectives | Possessive adjectives",
    "metadata_info": "Concatenation of page title, section title and table caption.",
    "header": [
        "Nominative",
        "Ergative",
        "Dative",
        "Genitive",
        "Instrumental",
        "Adverbial"
    ],
    "cell": [
        [
            "chem-i",
            "chem-ma",
            "chem-s",
            "chem-i",
            "chem-is",
            "chem-s"
        ],
        [
            "shen-i",
            "shen-ma",
            "shen-s",
            "shen-i",
            "shen-is",
            "shen-s"
        ],
        [
            "mis-i",
            "mis-ma",
            "mis",
            "mis-i",
            "mis-i",
            "mis"
        ],
        [
            "chven-i",
            "chven-ma",
            "chven-s",
            "chven-i",
            "chven-s",
            "chven-s"
        ],
        [
            "tkven-i",
            "tkven-ma",
            "tkven-s",
            "tkven-i",
            "tkven-s",
            "tkven-s"
        ],
        [
            "mat-i",
            "mat-ma",
            "mat",
            "mat-i",
            "mat-i",
            "mat"
        ]
    ],
    "source": "Open-WikiTable"
}