{
    "id": "42d3883c5b740bbbf448c41bc157bc03271aeaa39e09bcd792181ba14299f5e9",
    "metadata": "\u0141om\u017ca Governorate | Language | Language",
    "metadata_info": "Concatenation of page title, section title and table caption.",
    "header": [
        "Language_",
        "Number_",
        "percentage_",
        "males",
        "females"
    ],
    "cell": [
        [
            "Polish",
            "448 065",
            "77.3",
            "220 787",
            "227 278"
        ],
        [
            "Yiddish",
            "91 236",
            "15.74",
            "44 669",
            "46 567"
        ],
        [
            "Russian",
            "27 941",
            "4.82",
            "25 233",
            "2 708"
        ],
        [
            "German",
            "4 651",
            "0.8",
            "2 387",
            "2 264"
        ],
        [
            "Ukrainian",
            "3 832",
            "0.66",
            "3750",
            "82"
        ],
        [
            "Latvian",
            "2 509",
            "0.43",
            "2 502",
            "7"
        ],
        [
            "Other",
            "1 336",
            "0.23",
            "1 137",
            "199"
        ],
        [
            "Persons that didn`t name their native language",
            "14",
            ">0.01",
            "7",
            "7"
        ],
        [
            "Total",
            "579 592",
            "100",
            "300 487",
            "279 105"
        ]
    ],
    "source": "Open-WikiTable"
}