{
    "id": "e572b091b1deac82865fd45f17bb55807564efa718bcff22e10f19d2a1e743d7",
    "metadata": "1991 New Orleans Saints season | Schedule | Schedule",
    "metadata_info": "Concatenation of page title, section title and table caption.",
    "header": [
        "Week",
        "Date_",
        "Opponent",
        "Result_",
        "Record",
        "Attendance"
    ],
    "cell": [
        [
            "1",
            "September 1, 1991",
            "Seattle Seahawks",
            "W 27-24",
            "1-0",
            "68492"
        ],
        [
            "2",
            "September 8, 1991",
            "at Kansas City Chiefs",
            "W 17-10",
            "2-0",
            "74816"
        ],
        [
            "3",
            "September 15, 1991",
            "Los Angeles Rams",
            "W 24-7",
            "3-0",
            "68583"
        ],
        [
            "4",
            "September 22, 1991",
            "Minnesota Vikings",
            "W 26-0",
            "4-0",
            "68591"
        ],
        [
            "5",
            "September 29, 1991",
            "at Atlanta Falcons",
            "W 27-6",
            "5-0",
            "56556"
        ],
        [
            "6",
            "Bye",
            "Bye",
            "Bye",
            "Bye",
            "Bye"
        ],
        [
            "7",
            "October 13, 1991",
            "at Philadelphia Eagles",
            "W 13-6",
            "6-0",
            "64224"
        ],
        [
            "8",
            "October 20, 1991",
            "Tampa Bay Buccaneers",
            "W 23-7",
            "7-0",
            "68591"
        ],
        [
            "9",
            "October 27, 1991",
            "Chicago Bears",
            "L 20-17",
            "7-1",
            "68591"
        ],
        [
            "10",
            "November 3, 1991",
            "at Los Angeles Rams",
            "W 24-17",
            "8-1",
            "58713"
        ],
        [
            "11",
            "November 10, 1991",
            "San Francisco 49ers",
            "W 10-3",
            "9-1",
            "68591"
        ],
        [
            "12",
            "November 17, 1991",
            "at San Diego Chargers",
            "L 24-21",
            "9-2",
            "48420"
        ],
        [
            "13",
            "November 24, 1991",
            "Atlanta Falcons",
            "L 23-20",
            "9-3",
            "68591"
        ],
        [
            "14",
            "December 1, 1991",
            "at San Francisco 49ers",
            "L 38-24",
            "9-4",
            "62092"
        ],
        [
            "15",
            "December 8, 1991",
            "at Dallas Cowboys",
            "L 23-14",
            "9-5",
            "64530"
        ],
        [
            "16",
            "December 16, 1991",
            "Los Angeles Raiders",
            "W 27-0",
            "10-5",
            "68625"
        ],
        [
            "17",
            "December 22, 1991",
            "at Phoenix Cardinals",
            "W 27-3",
            "11-5",
            "30928"
        ]
    ],
    "source": "Open-WikiTable"
}