{
    "id": "9f012e0aaf7b2803fffc9cea6c415dcc42b060434663172a65d57cc254dc1f69",
    "metadata": "List of longest suspension bridge spans | Completed suspension bridges | Completed suspension bridges",
    "metadata_info": "Concatenation of page title, section title and table caption.",
    "header": [
        "Rank_",
        "Main_span_metres",
        "Main_span_feet",
        "Year_opened",
        "Country"
    ],
    "cell": [
        [
            "1",
            "1991",
            "6532",
            "1998",
            "Japan"
        ],
        [
            "2",
            "1650",
            "5413",
            "2009",
            "China"
        ],
        [
            "3",
            "1624",
            "5328",
            "1998",
            "Denmark"
        ],
        [
            "4",
            "1545",
            "5069",
            "2012",
            "South Korea"
        ],
        [
            "5",
            "1490",
            "4888",
            "2005",
            "China"
        ],
        [
            "6",
            "1418",
            "4652",
            "2012",
            "China"
        ],
        [
            "7",
            "1410",
            "4626",
            "1981",
            "United Kingdom"
        ],
        [
            "8",
            "1385",
            "4544",
            "1999",
            "China"
        ],
        [
            "9",
            "1377",
            "4518",
            "1997",
            "Hong Kong"
        ],
        [
            "10",
            "1310",
            "4298",
            "2013",
            "Norway"
        ],
        [
            "11",
            "1298",
            "4260",
            "1964",
            "United States"
        ],
        [
            "12",
            "1280",
            "4200",
            "1937",
            "United States"
        ],
        [
            "13",
            "1280",
            "4199",
            "2007",
            "China"
        ],
        [
            "14",
            "1210",
            "3970",
            "1997",
            "Sweden"
        ],
        [
            "15",
            "1176",
            "3858",
            "2012",
            "China"
        ],
        [
            "16",
            "1158",
            "3799",
            "1957",
            "United States"
        ],
        [
            "17",
            "1108",
            "3635",
            "2008",
            "China"
        ],
        [
            "18",
            "1100",
            "3609",
            "1989",
            "Japan"
        ],
        [
            "19",
            "1090",
            "3576",
            "1988",
            "Turkey"
        ],
        [
            "20",
            "1088",
            "3570",
            "2009",
            "China"
        ],
        [
            "21",
            "1,080 (x2)",
            "3,543 (x2)",
            "2012",
            "China"
        ],
        [
            "22",
            "1074",
            "3524",
            "1973",
            "Turkey"
        ],
        [
            "23",
            "1067",
            "3501",
            "1931",
            "United States"
        ],
        [
            "24",
            "1030",
            "3379",
            "1999",
            "Japan"
        ],
        [
            "25",
            "1020",
            "3346",
            "1999",
            "Japan"
        ],
        [
            "26",
            "1013",
            "3323",
            "1966",
            "Portugal"
        ],
        [
            "27",
            "1006",
            "3301",
            "1964",
            "United Kingdom"
        ],
        [
            "28",
            "990",
            "3248",
            "1988",
            "Japan"
        ],
        [
            "29",
            "988",
            "3241",
            "1966",
            "United Kingdom"
        ],
        [
            "30",
            "960",
            "3150",
            "2001",
            "China"
        ],
        [
            "31",
            "940",
            "3084",
            "1988",
            "Japan"
        ],
        [
            "32",
            "900",
            "2953",
            "1996",
            "China"
        ],
        [
            "33",
            "900",
            "2953",
            "2009",
            "China"
        ],
        [
            "34",
            "888",
            "2913",
            "1997",
            "China"
        ],
        [
            "35",
            "876",
            "2874",
            "1985",
            "Japan"
        ],
        [
            "36",
            "853",
            "2799",
            "1950",
            "United States"
        ],
        [
            "37",
            "853",
            "2799",
            "2007",
            "United States"
        ],
        [
            "38",
            "850",
            "2789",
            "1992",
            "Norway"
        ],
        [
            "39",
            "820",
            "2690",
            "2012",
            "China"
        ],
        [
            "40",
            "770",
            "2526",
            "1983",
            "Japan"
        ],
        [
            "41",
            "750",
            "2461",
            "2000",
            "Japan"
        ],
        [
            "42",
            "750",
            "2461",
            "2000",
            "Kazakhstan"
        ],
        [
            "43",
            "728",
            "2388",
            "2003",
            "United States"
        ],
        [
            "44",
            "720",
            "2362",
            "1998",
            "Japan"
        ],
        [
            "45",
            "712",
            "2336",
            "1967",
            "Venezuela"
        ],
        [
            "46",
            "712",
            "2336",
            "1973",
            "Japan"
        ],
        [
            "47",
            "704",
            "2310",
            "1936",
            "United States"
        ],
        [
            "48",
            "704",
            "2310",
            "1936",
            "United States"
        ],
        [
            "49",
            "701",
            "2300",
            "1939",
            "United States"
        ],
        [
            "50",
            "677",
            "2221",
            "2001",
            "Norway"
        ],
        [
            "51",
            "668",
            "2192",
            "1969",
            "Canada"
        ],
        [
            "52",
            "656",
            "2152",
            "1968",
            "United States"
        ],
        [
            "53",
            "656",
            "2152",
            "1951",
            "United States"
        ],
        [
            "54",
            "648",
            "2126",
            "1999",
            "China"
        ],
        [
            "55",
            "636",
            "2087",
            "2009",
            "China"
        ],
        [
            "56",
            "623",
            "2044",
            "1992",
            "Norway"
        ],
        [
            "57",
            "616",
            "2021",
            "2009",
            "China"
        ],
        [
            "58",
            "610",
            "2001",
            "1957",
            "United States"
        ],
        [
            "59",
            "608",
            "1995",
            "1959",
            "France"
        ],
        [
            "60",
            "600",
            "1969",
            "1970",
            "Denmark"
        ],
        [
            "61",
            "600",
            "1969",
            "1999",
            "Japan"
        ],
        [
            "62",
            "600",
            "1969",
            "2000",
            "China"
        ],
        [
            "63",
            "595",
            "1952",
            "1997",
            "Norway"
        ],
        [
            "64",
            "580",
            "1903",
            "2003",
            "China"
        ],
        [
            "65",
            "577",
            "1893",
            "2001",
            "Norway"
        ],
        [
            "66",
            "570",
            "1870",
            "1993",
            "Japan"
        ],
        [
            "67",
            "564",
            "1850",
            "1929",
            "United States Canada"
        ],
        [
            "68",
            "560",
            "1837",
            "1988",
            "Japan"
        ],
        [
            "69",
            "560",
            "1837",
            "2001",
            "China"
        ],
        [
            "70",
            "549",
            "1801",
            "1961",
            "United States"
        ],
        [
            "71",
            "540",
            "1772",
            "2008",
            "Japan"
        ],
        [
            "72",
            "534",
            "1752",
            "1926",
            "United States"
        ],
        [
            "73",
            "525",
            "1722",
            "1972",
            "Norway"
        ],
        [
            "74",
            "525",
            "1722",
            "1977",
            "Norway"
        ],
        [
            "75",
            "520",
            "1706",
            "1983",
            "Democratic Republic of the Congo"
        ],
        [
            "76",
            "500",
            "1640",
            "1965",
            "Germany"
        ],
        [
            "77",
            "500",
            "1640",
            "2002",
            "South Korea"
        ],
        [
            "78",
            "497",
            "1631",
            "1924",
            "United States"
        ],
        [
            "79",
            "488",
            "1601",
            "1903",
            "United States"
        ],
        [
            "80",
            "488",
            "1601",
            "1969",
            "United States"
        ],
        [
            "81",
            "488",
            "1601",
            "1952",
            "United States"
        ],
        [
            "82",
            "488",
            "1601",
            "1973",
            "United States"
        ],
        [
            "83",
            "486",
            "1594",
            "1883",
            "United States"
        ],
        [
            "84",
            "473",
            "1552",
            "1938",
            "Canada"
        ],
        [
            "85",
            "468",
            "1535",
            "1971",
            "Norway"
        ],
        [
            "86",
            "465",
            "1526",
            "1977",
            "Japan"
        ],
        [
            "87",
            "457",
            "1499",
            "1930",
            "United States"
        ],
        [
            "88",
            "457",
            "1499",
            "1963",
            "United States"
        ],
        [
            "89",
            "452",
            "1483",
            "1995",
            "China"
        ],
        [
            "90",
            "450",
            "1476",
            "1997",
            "China"
        ],
        [
            "91",
            "448",
            "1470",
            "1909",
            "United States"
        ],
        [
            "92",
            "446",
            "1463",
            "1997",
            "Norway"
        ],
        [
            "93",
            "441",
            "1447",
            "1955",
            "Canada"
        ],
        [
            "94",
            "430",
            "1411",
            "2012",
            "China"
        ],
        [
            "95",
            "427",
            "1401",
            "1970",
            "Canada"
        ],
        [
            "96",
            "421",
            "1381",
            "1936",
            "United States"
        ],
        [
            "97",
            "417",
            "1368",
            "1966",
            "Sweden"
        ],
        [
            "98",
            "408",
            "1339",
            "2010",
            "China"
        ],
        [
            "99",
            "405",
            "1329",
            "2009",
            "Vietnam"
        ],
        [
            "100",
            "404",
            "1325",
            "1973",
            "South Korea"
        ],
        [
            "101",
            "394",
            "1293",
            "1967",
            "France"
        ],
        [
            "102",
            "390",
            "1280",
            "1964",
            "Uzbekistan"
        ],
        [
            "103",
            "385",
            "1263",
            "2013",
            "United States"
        ],
        [
            "104",
            "378",
            "1240",
            "1954",
            "Germany"
        ],
        [
            "105",
            "368",
            "1207",
            "1931",
            "United States"
        ],
        [
            "106",
            "367",
            "1204",
            "1962",
            "Japan"
        ],
        [
            "107",
            "366",
            "1200",
            "1929",
            "United States"
        ],
        [
            "108",
            "351",
            "1151",
            "1960",
            "United States Canada"
        ],
        [
            "109",
            "350",
            "1148",
            "2006",
            "China"
        ],
        [
            "110",
            "340",
            "1115",
            "1926",
            "Brazil"
        ],
        [
            "111",
            "338",
            "1109",
            "2001",
            "China"
        ],
        [
            "112",
            "338",
            "1108",
            "1965",
            "United States"
        ],
        [
            "113",
            "337",
            "1106",
            "1956",
            "Norway"
        ],
        [
            "114",
            "335",
            "1100",
            "1961",
            "United Kingdom"
        ],
        [
            "115",
            "335",
            "1100",
            "2006",
            "Norway"
        ],
        [
            "116",
            "329",
            "1088",
            "1939",
            "United States"
        ],
        [
            "117",
            "328",
            "1085",
            "1939",
            "Zambia Zimbabwe"
        ],
        [
            "118",
            "325",
            "1066",
            "1964",
            "Norway"
        ],
        [
            "119",
            "325",
            "1066",
            "1981",
            "Norway"
        ],
        [
            "120",
            "323",
            "1060",
            "1932",
            "United States"
        ],
        [
            "121",
            "323",
            "1059",
            "1936",
            "Canada"
        ],
        [
            "122",
            "322",
            "1057",
            "1867",
            "United States"
        ],
        [
            "123",
            "320",
            "1050",
            "1971",
            "United States"
        ],
        [
            "124",
            "320",
            "1050",
            "2011",
            "Peru"
        ],
        [
            "125",
            "315",
            "1033",
            "1951",
            "Germany"
        ],
        [
            "126",
            "308",
            "1010",
            "1849",
            "United States"
        ],
        [
            "127",
            "300",
            "985",
            "1961",
            "Canada"
        ],
        [
            "128",
            "300",
            "984",
            "1987",
            "Japan"
        ],
        [
            "129",
            "300",
            "984",
            "2000",
            "France"
        ],
        [
            "130",
            "300",
            "984",
            "2000",
            "South Korea"
        ]
    ],
    "source": "Open-WikiTable"
}