{
    "id": "68f0b71b7a780d09632887c4e689586ad8c6740132fbdf2790c929404d4340e7",
    "metadata": "John Isner | Singles: 16 (7 titles, 9 runners-up) | Singles: 16 (7 titles, 9 runners-up)",
    "metadata_info": "Concatenation of page title, section title and table caption.",
    "header": [
        "Outcome",
        "Date_",
        "Surface",
        "Opponent",
        "Score"
    ],
    "cell": [
        [
            "Runner-up",
            "August 5, 2007",
            "Hard",
            "Andy Roddick",
            "4-6, 6-7 (4-7)"
        ],
        [
            "Winner",
            "January 16, 2010",
            "Hard",
            "Arnaud Cl\u00e9ment",
            "6-3, 5-7, 7-6 (7-2)"
        ],
        [
            "Runner-up",
            "February 21, 2010",
            "Hard (i)",
            "Sam Querrey",
            "7-6 (7-3) , 6-7 (5-7) , 3-6"
        ],
        [
            "Runner-up",
            "May 9, 2010",
            "Clay",
            "Sam Querrey",
            "6-3, 6-7 (4-7) , 4-6"
        ],
        [
            "Runner-up",
            "July 25, 2010",
            "Hard",
            "Mardy Fish",
            "6-4, 4-6, 6-7 (4-7)"
        ],
        [
            "Winner",
            "July 10, 2011",
            "Grass",
            "Olivier Rochus",
            "6-3, 7-6 (8-6)"
        ],
        [
            "Runner-up",
            "July 24, 2011",
            "Hard",
            "Mardy Fish",
            "6-3, 6-7 (6-8) , 2-6"
        ],
        [
            "Winner",
            "August 27, 2011",
            "Hard",
            "Julien Benneteau",
            "4-6, 6-3, 6-4"
        ],
        [
            "Runner-up",
            "March 18, 2012",
            "Hard",
            "Roger Federer",
            "6-7 (7-9) , 3-6"
        ],
        [
            "Runner-up",
            "April 15, 2012",
            "Clay",
            "Juan M\u00f3naco",
            "2-6, 6-3, 3-6"
        ],
        [
            "Winner",
            "July 15, 2012",
            "Grass",
            "Lleyton Hewitt",
            "7-6 (7-1) , 6-4"
        ],
        [
            "Winner",
            "August 25, 2012",
            "Hard",
            "Tom\u00e1\u0161 Berdych",
            "3-6, 6-4, 7-6 (11-9)"
        ],
        [
            "Winner",
            "April 14, 2013",
            "Clay",
            "Nicol\u00e1s Almagro",
            "6-3, 7-5"
        ],
        [
            "Winner",
            "July 28, 2013",
            "Hard",
            "Kevin Anderson",
            "6-7 (3-7) , 7-6 (7-2) , 7-6 (7-2)"
        ],
        [
            "Runner-up",
            "August 4, 2013",
            "Hard",
            "Juan Mart\u00edn del Potro",
            "6-3, 1-6, 2-6"
        ],
        [
            "Runner-up",
            "August 18, 2013",
            "Hard",
            "Rafael Nadal",
            "6-7 (8-10) , 6-7 (3-7)"
        ]
    ],
    "source": "Open-WikiTable"
}