{
    "id": "dc7d4a5e7cc1543fd8b2822c8a89088ce18cb27de3f37be822980aa35362b4b9",
    "metadata": "Circuit des Nations | Geneva race-track (Switzerland) | Geneva race-track (Switzerland)",
    "metadata_info": "Concatenation of page title, section title and table caption.",
    "header": [
        "Date_",
        "Race",
        "Race_track",
        "Category",
        "Lap_length"
    ],
    "cell": [
        [
            "July 21, 1946",
            "1st Grand Prix des Nations",
            "Circuit des Nations",
            "Grand Prix FIA",
            "km (mi)Switzerland"
        ],
        [
            "May 2, 1948",
            "2nd Grand Prix de Gen\u00e8ve",
            "Circuit des Nations",
            "Formula 2 FIA, non-championship",
            "km (mi)"
        ],
        [
            "May 2, 1948",
            "2nd Grand Prix des Nations",
            "Circuit des Nations",
            "Formula 1 FIA, non-championship",
            "km (mi)"
        ],
        [
            "July 30, 1950",
            "3rd Grand Prix de Gen\u00e8ve",
            "Circuit des Nations",
            "Formula 2 FIA, non-championship",
            "km (mi)"
        ],
        [
            "July 30, 1950",
            "3rd Grand Prix des Nations",
            "Circuit des Nations",
            "Formula 1 FIA, non-championship",
            "km (mi)"
        ]
    ],
    "source": "Open-WikiTable"
}